[{"created_at":"Tue Feb 23 04:05:58 +0000 2016","id":701981298852810752,"id_str":"701981298852810752","text":"Just sorting a project on the Twitter API @Andela.","source":"\u003ca href=\"http:\/\/andela.com\" rel=\"nofollow\"\u003eAndela Sentiment Analyzer\u003c\/a\u003e","truncated":false,"in_reply_to_status_id":null,"in_reply_to_status_id_str":null,"in_reply_to_user_id":null,"in_reply_to_user_id_str":null,"in_reply_to_screen_name":null,"user":{"id":212657683,"id_str":"212657683","name":"Mubarak Ade IMAM","screen_name":"MubarakAdeImam","location":"Lagos, Nigeria","description":"I am satisfied with Allah as my Lord, Muhammad as his messenger and Qur'an as my guide.","url":"http:\/\/t.co\/gS9kYfJsS4","entities":{"url":{"urls":[{"url":"http:\/\/t.co\/gS9kYfJsS4","expanded_url":"http:\/\/about.me\/mubarakadeimam","display_url":"about.me\/mubarakadeimam","indices":[0,22]}]},"description":{"urls":[]}},"protected":false,"followers_count":78,"friends_count":281,"listed_count":0,"created_at":"Sat Nov 06 17:47:58 +0000 2010","favourites_count":4,"utc_offset":3600,"time_zone":"West Central Africa","geo_enabled":false,"verified":false,"statuses_count":257,"lang":"en","contributors_enabled":false,"is_translator":false,"is_translation_enabled":false,"profile_background_color":"C0DEED","profile_background_image_url":"http:\/\/pbs.twimg.com\/profile_background_images\/820452311\/5bd730dbee68537422bbe6d533c4598e.jpeg","profile_background_image_url_https":"https:\/\/pbs.twimg.com\/profile_background_images\/820452311\/5bd730dbee68537422bbe6d533c4598e.jpeg","profile_background_tile":false,"profile_image_url":"http:\/\/pbs.twimg.com\/profile_images\/577164900851576832\/_t89qvZB_normal.jpeg","profile_image_url_https":"https:\/\/pbs.twimg.com\/profile_images\/577164900851576832\/_t89qvZB_normal.jpeg","profile_banner_url":"https:\/\/pbs.twimg.com\/profile_banners\/212657683\/1401297927","profile_link_color":"4A913C","profile_sidebar_border_color":"FFFFFF","profile_sidebar_fill_color":"DDEEF6","profile_text_color":"333333","profile_use_background_image":true,"has_extended_profile":true,"default_profile":false,"default_profile_image":false,"following":false,"follow_request_sent":false,"notifications":false},"geo":null,"coordinates":null,"place":null,"contributors":null,"is_quote_status":false,"retweet_count":0,"favorite_count":1,"entities":{"hashtags":[],"symbols":[],"user_mentions":[{"screen_name":"Andela","name":"Andela","id":1378315837,"id_str":"1378315837","indices":[42,49]}],"urls":[]},"favorited":false,"retweeted":false,"lang":"en"},{"created_at":"Mon Feb 15 15:35:24 +0000 2016","id":699255696605515776,"id_str":"699255696605515776","text":"Lagos on Rails \u2014 are you attending? #lagosonrails https:\/\/t.co\/KeyB6tQxzH via @attending","source":"\u003ca href=\"http:\/\/twitter.com\" rel=\"nofollow\"\u003eTwitter Web Client\u003c\/a\u003e","truncated":false,"in_reply_to_status_id":null,"in_reply_to_status_id_str":null,"in_reply_to_user_id":null,"in_reply_to_user_id_str":null,"in_reply_to_screen_name":null,"user":{"id":212657683,"id_str":"212657683","name":"Mubarak Ade IMAM","screen_name":"MubarakAdeImam","location":"Lagos, Nigeria","description":"I am satisfied with Allah as my Lord, Muhammad as his messenger and Qur'an as my guide.","url":"http:\/\/t.co\/gS9kYfJsS4","entities":{"url":{"urls":[{"url":"http:\/\/t.co\/gS9kYfJsS4","expanded_url":"http:\/\/about.me\/mubarakadeimam","display_url":"about.me\/mubarakadeimam","indices":[0,22]}]},"description":{"urls":[]}},"protected":false,"followers_count":78,"friends_count":281,"listed_count":0,"created_at":"Sat Nov 06 17:47:58 +0000 2010","favourites_count":4,"utc_offset":3600,"time_zone":"West Central Africa","geo_enabled":false,"verified":false,"statuses_count":257,"lang":"en","contributors_enabled":false,"is_translator":false,"is_translation_enabled":false,"profile_background_color":"C0DEED","profile_background_image_url":"http:\/\/pbs.twimg.com\/profile_background_images\/820452311\/5bd730dbee68537422bbe6d533c4598e.jpeg","profile_background_image_url_https":"https:\/\/pbs.twimg.com\/profile_background_images\/820452311\/5bd730dbee68537422bbe6d533c4598e.jpeg","profile_background_tile":false,"profile_image_url":"http:\/\/pbs.twimg.com\/profile_images\/577164900851576832\/_t89qvZB_normal.jpeg","profile_image_url_https":"https:\/\/pbs.twimg.com\/profile_images\/577164900851576832\/_t89qvZB_normal.jpeg","profile_banner_url":"https:\/\/pbs.twimg.com\/profile_banners\/212657683\/1401297927","profile_link_color":"4A913C","profile_sidebar_border_color":"FFFFFF","profile_sidebar_fill_color":"DDEEF6","profile_text_color":"333333","profile_use_background_image":true,"has_extended_profile":true,"default_profile":false,"default_profile_image":false,"following":false,"follow_request_sent":false,"notifications":false},"geo":null,"coordinates":null,"place":null,"contributors":null,"is_quote_status":false,"retweet_count":0,"favorite_count":0,"entities":{"hashtags":[{"text":"lagosonrails","indices":[36,49]}],"symbols":[],"user_mentions":[{"screen_name":"attending","name":"Attending","id":1606040299,"id_str":"1606040299","indices":[78,88]}],"urls":[{"url":"https:\/\/t.co\/KeyB6tQxzH","expanded_url":"http:\/\/attending.io\/events\/lagosonrails-1621ab6c-0c9e-4d0d-b444-ac364e44d09f","display_url":"attending.io\/events\/lagoson\u2026","indices":[50,73]}]},"favorited":false,"retweeted":false,"possibly_sensitive":false,"lang":"en"},{"created_at":"Fri Feb 12 22:27:01 +0000 2016","id":698272121336811520,"id_str":"698272121336811520","text":"#THELABISHOW\nLove should be shown everyday, but I think women especially fancies, #Everyday, #Anniversaries, and then again #Everyday.","source":"\u003ca href=\"https:\/\/mobile.twitter.com\" rel=\"nofollow\"\u003eMobile Web (M2)\u003c\/a\u003e","truncated":false,"in_reply_to_status_id":null,"in_reply_to_status_id_str":null,"in_reply_to_user_id":null,"in_reply_to_user_id_str":null,"in_reply_to_screen_name":null,"user":{"id":212657683,"id_str":"212657683","name":"Mubarak Ade IMAM","screen_name":"MubarakAdeImam","location":"Lagos, Nigeria","description":"I am satisfied with Allah as my Lord, Muhammad as his messenger and Qur'an as my guide.","url":"http:\/\/t.co\/gS9kYfJsS4","entities":{"url":{"urls":[{"url":"http:\/\/t.co\/gS9kYfJsS4","expanded_url":"http:\/\/about.me\/mubarakadeimam","display_url":"about.me\/mubarakadeimam","indices":[0,22]}]},"description":{"urls":[]}},"protected":false,"followers_count":78,"friends_count":281,"listed_count":0,"created_at":"Sat Nov 06 17:47:58 +0000 2010","favourites_count":4,"utc_offset":3600,"time_zone":"West Central Africa","geo_enabled":false,"verified":false,"statuses_count":257,"lang":"en","contributors_enabled":false,"is_translator":false,"is_translation_enabled":false,"profile_background_color":"C0DEED","profile_background_image_url":"http:\/\/pbs.twimg.com\/profile_background_images\/820452311\/5bd730dbee68537422bbe6d533c4598e.jpeg","profile_background_image_url_https":"https:\/\/pbs.twimg.com\/profile_background_images\/820452311\/5bd730dbee68537422bbe6d533c4598e.jpeg","profile_background_tile":false,"profile_image_url":"http:\/\/pbs.twimg.com\/profile_images\/577164900851576832\/_t89qvZB_normal.jpeg","profile_image_url_https":"https:\/\/pbs.twimg.com\/profile_images\/577164900851576832\/_t89qvZB_normal.jpeg","profile_banner_url":"https:\/\/pbs.twimg.com\/profile_banners\/212657683\/1401297927","profile_link_color":"4A913C","profile_sidebar_border_color":"FFFFFF","profile_sidebar_fill_color":"DDEEF6","profile_text_color":"333333","profile_use_background_image":true,"has_extended_profile":true,"default_profile":false,"default_profile_image":false,"following":false,"follow_request_sent":false,"notifications":false},"geo":null,"coordinates":null,"place":null,"contributors":null,"is_quote_status":false,"retweet_count":0,"favorite_count":0,"entities":{"hashtags":[{"text":"THELABISHOW","indices":[0,12]},{"text":"Everyday","indices":[82,91]},{"text":"Anniversaries","indices":[93,107]},{"text":"Everyday","indices":[124,133]}],"symbols":[],"user_mentions":[],"urls":[]},"favorited":false,"retweeted":false,"lang":"en"},{"created_at":"Fri Jan 08 02:36:43 +0000 2016","id":685288994939232256,"id_str":"685288994939232256","text":"Which are your most used words on Facebook? https:\/\/t.co\/IluinSXMlY","source":"\u003ca href=\"http:\/\/www.facebook.com\/twitter\" rel=\"nofollow\"\u003eFacebook\u003c\/a\u003e","truncated":false,"in_reply_to_status_id":null,"in_reply_to_status_id_str":null,"in_reply_to_user_id":null,"in_reply_to_user_id_str":null,"in_reply_to_screen_name":null,"user":{"id":212657683,"id_str":"212657683","name":"Mubarak Ade IMAM","screen_name":"MubarakAdeImam","location":"Lagos, Nigeria","description":"I am satisfied with Allah as my Lord, Muhammad as his messenger and Qur'an as my guide.","url":"http:\/\/t.co\/gS9kYfJsS4","entities":{"url":{"urls":[{"url":"http:\/\/t.co\/gS9kYfJsS4","expanded_url":"http:\/\/about.me\/mubarakadeimam","display_url":"about.me\/mubarakadeimam","indices":[0,22]}]},"description":{"urls":[]}},"protected":false,"followers_count":78,"friends_count":281,"listed_count":0,"created_at":"Sat Nov 06 17:47:58 +0000 2010","favourites_count":4,"utc_offset":3600,"time_zone":"West Central Africa","geo_enabled":false,"verified":false,"statuses_count":257,"lang":"en","contributors_enabled":false,"is_translator":false,"is_translation_enabled":false,"profile_background_color":"C0DEED","profile_background_image_url":"http:\/\/pbs.twimg.com\/profile_background_images\/820452311\/5bd730dbee68537422bbe6d533c4598e.jpeg","profile_background_image_url_https":"https:\/\/pbs.twimg.com\/profile_background_images\/820452311\/5bd730dbee68537422bbe6d533c4598e.jpeg","profile_background_tile":false,"profile_image_url":"http:\/\/pbs.twimg.com\/profile_images\/577164900851576832\/_t89qvZB_normal.jpeg","profile_image_url_https":"https:\/\/pbs.twimg.com\/profile_images\/577164900851576832\/_t89qvZB_normal.jpeg","profile_banner_url":"https:\/\/pbs.twimg.com\/profile_banners\/212657683\/1401297927","profile_link_color":"4A913C","profile_sidebar_border_color":"FFFFFF","profile_sidebar_fill_color":"DDEEF6","profile_text_color":"333333","profile_use_background_image":true,"has_extended_profile":true,"default_profile":false,"default_profile_image":false,"following":false,"follow_request_sent":false,"notifications":false},"geo":null,"coordinates":null,"place":null,"contributors":null,"is_quote_status":false,"retweet_count":0,"favorite_count":0,"entities":{"hashtags":[],"symbols":[],"user_mentions":[],"urls":[{"url":"https:\/\/t.co\/IluinSXMlY","expanded_url":"http:\/\/fb.me\/6UjjvPwDr","display_url":"fb.me\/6UjjvPwDr","indices":[44,67]}]},"favorited":false,"retweeted":false,"possibly_sensitive":false,"lang":"en"},{"created_at":"Fri Jan 08 02:13:53 +0000 2016","id":685283248658903040,"id_str":"685283248658903040","text":"A heart-touching reminder. https:\/\/t.co\/Ytg7a7iyFT","source":"\u003ca href=\"http:\/\/www.facebook.com\/twitter\" rel=\"nofollow\"\u003eFacebook\u003c\/a\u003e","truncated":false,"in_reply_to_status_id":null,"in_reply_to_status_id_str":null,"in_reply_to_user_id":null,"in_reply_to_user_id_str":null,"in_reply_to_screen_name":null,"user":{"id":212657683,"id_str":"212657683","name":"Mubarak Ade IMAM","screen_name":"MubarakAdeImam","location":"Lagos, Nigeria","description":"I am satisfied with Allah as my Lord, Muhammad as his messenger and Qur'an as my guide.","url":"http:\/\/t.co\/gS9kYfJsS4","entities":{"url":{"urls":[{"url":"http:\/\/t.co\/gS9kYfJsS4","expanded_url":"http:\/\/about.me\/mubarakadeimam","display_url":"about.me\/mubarakadeimam","indices":[0,22]}]},"description":{"urls":[]}},"protected":false,"followers_count":78,"friends_count":281,"listed_count":0,"created_at":"Sat Nov 06 17:47:58 +0000 2010","favourites_count":4,"utc_offset":3600,"time_zone":"West Central Africa","geo_enabled":false,"verified":false,"statuses_count":257,"lang":"en","contributors_enabled":false,"is_translator":false,"is_translation_enabled":false,"profile_background_color":"C0DEED","profile_background_image_url":"http:\/\/pbs.twimg.com\/profile_background_images\/820452311\/5bd730dbee68537422bbe6d533c4598e.jpeg","profile_background_image_url_https":"https:\/\/pbs.twimg.com\/profile_background_images\/820452311\/5bd730dbee68537422bbe6d533c4598e.jpeg","profile_background_tile":false,"profile_image_url":"http:\/\/pbs.twimg.com\/profile_images\/577164900851576832\/_t89qvZB_normal.jpeg","profile_image_url_https":"https:\/\/pbs.twimg.com\/profile_images\/577164900851576832\/_t89qvZB_normal.jpeg","profile_banner_url":"https:\/\/pbs.twimg.com\/profile_banners\/212657683\/1401297927","profile_link_color":"4A913C","profile_sidebar_border_color":"FFFFFF","profile_sidebar_fill_color":"DDEEF6","profile_text_color":"333333","profile_use_background_image":true,"has_extended_profile":true,"default_profile":false,"default_profile_image":false,"following":false,"follow_request_sent":false,"notifications":false},"geo":null,"coordinates":null,"place":null,"contributors":null,"is_quote_status":false,"retweet_count":0,"favorite_count":0,"entities":{"hashtags":[],"symbols":[],"user_mentions":[],"urls":[{"url":"https:\/\/t.co\/Ytg7a7iyFT","expanded_url":"http:\/\/fb.me\/4gaLxRHbx","display_url":"fb.me\/4gaLxRHbx","indices":[27,50]}]},"favorited":false,"retweeted":false,"possibly_sensitive":false,"lang":"en"}]